LICENSE
README.md
setup.py
dblp_crawler/__init__.py
dblp_crawler/__main__.py
dblp_crawler/arg.py
dblp_crawler/downloader.py
dblp_crawler/gather.py
dblp_crawler/graph.py
dblp_crawler/journal.py
dblp_crawler/parser.py
dblp_crawler.egg-info/PKG-INFO
dblp_crawler.egg-info/SOURCES.txt
dblp_crawler.egg-info/dependency_links.txt
dblp_crawler.egg-info/requires.txt
dblp_crawler.egg-info/top_level.txt
dblp_crawler/data/__init__.py
dblp_crawler/data/neo4j.py
dblp_crawler/data/ccf/CCF_A.py
dblp_crawler/data/ccf/CCF_B.py
dblp_crawler/data/ccf/CCF_C.py
dblp_crawler/data/ccf/__init__.py
dblp_crawler/data/ccf/key.py
dblp_crawler/data/ccf/parse.py
dblp_crawler/filter/__init__.py
dblp_crawler/filter/__main__.py
dblp_crawler/filter/utils.py
dblp_crawler/keyword/__init__.py
dblp_crawler/keyword/arg.py
dblp_crawler/summarizer/__init__.py
dblp_crawler/summarizer/neo4j.py
dblp_crawler/summarizer/networkx.py