Metadata-Version: 2.1
Name: dblp-crawler
Version: 2.1.4.1
Summary: 异步高并发dblp爬虫，慎用
Home-page: https://github.com/yindaheng98/dblp-crawler
Author: yindaheng98
Author-email: yindaheng98@gmail.com
License: UNKNOWN
Platform: UNKNOWN
Classifier: Programming Language :: Python :: 3
Classifier: License :: OSI Approved :: MIT License
Classifier: Operating System :: OS Independent
License-File: LICENSE
